{
  "the year-[de.noun.en]-Jahr": {
    "priorParams": [
      1.2758433692996565,
      0.9999999999999949,
      1623539.4170187458
    ],
    "numDrills": 5,
    "lastTime": 1608756265,
    "lastResult": true
  },
  "Jahr-[de.noun.gender]-das": {
    "priorParams": [
      0.9046229036064263,
      1.3139547318888092,
      2647858.238339239
    ],
    "numDrills": 10,
    "lastTime": 1609631233,
    "lastResult": true
  },
  "the time/occurrence-[de.noun.en]-Mal": {
    "priorParams": [
      1.2865040074174954,
      0.9999999999999992,
      2348170.68783497
    ],
    "numDrills": 7,
    "lastTime": 1609874966,
    "lastResult": true
  },
  "Mal-[de.noun.gender]-das": {
    "priorParams": [
      4.351061964234011,
      6.448442633624525,
      414631.77282229677
    ],
    "numDrills": 24,
    "lastTime": 1609787805,
    "lastResult": true
  },
  "the example-[de.noun.en]-Beispiel": {
    "priorParams": [
      1.286496767739352,
      0.9999999999999878,
      2348170.68783497
    ],
    "numDrills": 7,
    "lastTime": 1609874989,
    "lastResult": true
  },
  "Beispiel-[de.noun.gender]-das": {
    "priorParams": [
      6.233602798097402,
      3.666902785431705,
      367703.28603280237
    ],
    "numDrills": 22,
    "lastTime": 1609529274,
    "lastResult": true
  },
  "the time-[de.noun.en]-Zeit": {
    "priorParams": [
      1.2758877168524516,
      0.9999999999999991,
      1623539.4170187458
    ],
    "numDrills": 5,
    "lastTime": 1608756297,
    "lastResult": true
  },
  "Zeit-[de.noun.gender]-die": {
    "priorParams": [
      1.1986649925330357,
      0.9999999999999787,
      2348170.68783497
    ],
    "numDrills": 7,
    "lastTime": 1609787584,
    "lastResult": true
  },
  "the woman/wife-[de.noun.en]-Frau": {
    "priorParams": [
      1.2758236592761967,
      1.0000000000000067,
      1623539.4170187458
    ],
    "numDrills": 5,
    "lastTime": 1608756211,
    "lastResult": true
  },
  "Frau-[de.noun.gender]-die": {
    "priorParams": [
      1.1986671218501657,
      0.9999999999999989,
      2348170.68783497
    ],
    "numDrills": 7,
    "lastTime": 1609787586,
    "lastResult": true
  },
  "the man/human-[de.noun.en]-Mensch": {
    "priorParams": [
      1.0049939344729226,
      1.3293457015029928,
      2647858.238339239
    ],
    "numDrills": 9,
    "lastTime": 1609787595,
    "lastResult": true
  },
  "Mensch-[de.noun.gender]-der": {
    "priorParams": [
      1.1986675477135753,
      1.0000000000000457,
      2348170.68783497
    ],
    "numDrills": 7,
    "lastTime": 1609787566,
    "lastResult": true
  },
  "the child-[de.noun.en]-Kind": {
    "priorParams": [
      0.7064309459305521,
      0.9999999999999962,
      2647858.238339239
    ],
    "numDrills": 7,
    "lastTime": 1608756293,
    "lastResult": true
  },
  "Kind-[de.noun.gender]-das": {
    "priorParams": [
      1.1986577528548783,
      0.9999999999999991,
      2348170.68783497
    ],
    "numDrills": 7,
    "lastTime": 1609787569,
    "lastResult": true
  },
  "the day-[de.noun.en]-Tag": {
    "priorParams": [
      1.256780080983052,
      0.9999999999999847,
      1623539.4170187458
    ],
    "numDrills": 4,
    "lastTime": 1608756259,
    "lastResult": true
  },
  "Tag-[de.noun.gender]-der": {
    "priorParams": [
      1.1986662701232977,
      1.0000000000000187,
      2348170.68783497
    ],
    "numDrills": 7,
    "lastTime": 1609787568,
    "lastResult": true
  },
  "the man/husband-[de.noun.en]-Mann": {
    "priorParams": [
      1.2569279061590142,
      0.9999999999999947,
      1623539.4170187458
    ],
    "numDrills": 5,
    "lastTime": 1608756282,
    "lastResult": true
  },
  "Mann-[de.noun.gender]-der": {
    "priorParams": [
      1.1986658442598772,
      1.0000000000000004,
      2348170.68783497
    ],
    "numDrills": 7,
    "lastTime": 1609787565,
    "lastResult": true
  },
  "the land/country-[de.noun.en]-Land": {
    "priorParams": [
      0.7064222596649223,
      0.9999999999999862,
      2647858.238339239
    ],
    "numDrills": 7,
    "lastTime": 1608756220,
    "lastResult": true
  },
  "Land-[de.noun.gender]-das": {
    "priorParams": [
      7.7971827475029905,
      4.414742458101488,
      317790.34512605733
    ],
    "numDrills": 22,
    "lastTime": 1609836689,
    "lastResult": true
  },
  "the question-[de.noun.en]-Frage": {
    "priorParams": [
      0.7064305682668325,
      1.0000000000000053,
      2647858.238339239
    ],
    "numDrills": 7,
    "lastTime": 1608756264,
    "lastResult": true
  },
  "Frage-[de.noun.gender]-die": {
    "priorParams": [
      1.198656475264645,
      0.9999999999999948,
      2348170.68783497
    ],
    "numDrills": 7,
    "lastTime": 1609787581,
    "lastResult": true
  },
  "the house/home-[de.noun.en]-Haus": {
    "priorParams": [
      1.2567505159478671,
      1.0000000000000113,
      1623539.4170187458
    ],
    "numDrills": 4,
    "lastTime": 1608756232,
    "lastResult": true
  },
  "Haus-[de.noun.gender]-das": {
    "priorParams": [
      1.1986138889225975,
      0.9999999999999758,
      2348170.68783497
    ],
    "numDrills": 7,
    "lastTime": 1609787546,
    "lastResult": true
  },
  "the fall-[de.noun.en]-Fall": {
    "priorParams": [
      0.7064415205148046,
      1.0000000000000184,
      2647858.238339239
    ],
    "numDrills": 7,
    "lastTime": 1608756274,
    "lastResult": true
  },
  "Fall-[de.noun.gender]-der": {
    "priorParams": [
      0.7036246365777549,
      1.000000000000146,
      2409469.3560557133
    ],
    "numDrills": 12,
    "lastTime": 1608671890,
    "lastResult": true
  },
  "the people-[de.noun.en]-Leute": {
    "priorParams": [
      1.236173764981472,
      0.9999999999999916,
      2348170.6878349707
    ],
    "numDrills": 7,
    "lastTime": 1609787889,
    "lastResult": true
  },
  "Leute-[de.noun.gender]-plu": {
    "priorParams": [
      1.1986317751862763,
      0.9999999999999899,
      2348170.68783497
    ],
    "numDrills": 7,
    "lastTime": 1609787575,
    "lastResult": true
  },
  "the work-[de.noun.en]-Arbeit": {
    "priorParams": [
      1.2020071576601865,
      0.999999999999994,
      1623539.4170187458
    ],
    "numDrills": 4,
    "lastTime": 1608667910,
    "lastResult": true
  },
  "Arbeit-[de.noun.gender]-die": {
    "priorParams": [
      1.1986232579178506,
      0.9999999999999974,
      2348170.68783497
    ],
    "numDrills": 7,
    "lastTime": 1609787550,
    "lastResult": true
  },
  "the percent-[de.noun.en]-Prozent": {
    "priorParams": [
      1.0963536332748796,
      1.0000000000000042,
      2647858.238339239
    ],
    "numDrills": 7,
    "lastTime": 1609787885,
    "lastResult": true
  },
  "Prozent-[de.noun.gender]-das": {
    "priorParams": [
      5.696173047049034,
      4.939970911911312,
      414631.77282229677
    ],
    "numDrills": 26,
    "lastTime": 1609787482,
    "lastResult": true
  },
  "the hand-[de.noun.en]-Hand": {
    "priorParams": [
      0.7751212918757598,
      0.9999999999981679,
      2409469.356055713
    ],
    "numDrills": 7,
    "lastTime": 1608756256,
    "lastResult": true
  },
  "Hand-[de.noun.gender]-die": {
    "priorParams": [
      2.8966270005558354,
      1.99723932426082,
      766072.9240637763
    ],
    "numDrills": 10,
    "lastTime": 1609529245,
    "lastResult": true
  },
  "the town-[de.noun.en]-Stadt": {
    "priorParams": [
      0.774717468518781,
      1.000000000005261,
      2409469.356055713
    ],
    "numDrills": 7,
    "lastTime": 1608755331,
    "lastResult": true
  },
  "Stadt-[de.noun.gender]-die": {
    "priorParams": [
      1.9811710273400753,
      1.9166514038274944,
      766072.9240637763
    ],
    "numDrills": 8,
    "lastTime": 1609788095,
    "lastResult": true
  },
  "the gentleman-[de.noun.en]-Herr": {
    "priorParams": [
      1.201990527327919,
      1.000000000000019,
      1623539.4170187458
    ],
    "numDrills": 4,
    "lastTime": 1608667899,
    "lastResult": true
  },
  "Herr-[de.noun.gender]-der": {
    "priorParams": [
      1.1986283682789165,
      1.0000000000000204,
      2348170.68783497
    ],
    "numDrills": 7,
    "lastTime": 1609787553,
    "lastResult": true
  },
  "the part/section-[de.noun.en]-Teil": {
    "priorParams": [
      1.2360575042677415,
      1.000000000000008,
      2348170.6878349707
    ],
    "numDrills": 7,
    "lastTime": 1609787796,
    "lastResult": true
  },
  "Teil-[de.noun.gender]-der": {
    "priorParams": [
      2.005089408039348,
      3.821652422055889,
      886394.2402254909
    ],
    "numDrills": 22,
    "lastTime": 1609787442,
    "lastResult": true
  },
  "the problem-[de.noun.en]-Problem": {
    "priorParams": [
      1.0963642078591014,
      0.9999999999999908,
      2647858.238339239
    ],
    "numDrills": 7,
    "lastTime": 1609787877,
    "lastResult": true
  },
  "Problem-[de.noun.gender]-das": {
    "priorParams": [
      1.1986126113323476,
      0.9999999999999787,
      2348170.68783497
    ],
    "numDrills": 7,
    "lastTime": 1609787561,
    "lastResult": true
  },
  "the world-[de.noun.en]-Welt": {
    "priorParams": [
      2.572602236354695,
      1.7180861309418751,
      863843.7204158901
    ],
    "numDrills": 10,
    "lastTime": 1609276314,
    "lastResult": true
  },
  "Welt-[de.noun.gender]-die": {
    "priorParams": [
      10.317927894216817,
      6.029138825460434,
      213143.23576551175
    ],
    "numDrills": 22,
    "lastTime": 1609811600,
    "lastResult": true
  },
  "the right/law-[de.noun.en]-Recht": {
    "priorParams": [
      0.7966069117933965,
      0.9999999999999991,
      2348170.6878349707
    ],
    "numDrills": 7,
    "lastTime": 1608756267,
    "lastResult": true
  },
  "Recht-[de.noun.gender]-das": {
    "priorParams": [
      1.1985759870782435,
      0.9999999999999631,
      2348170.68783497
    ],
    "numDrills": 7,
    "lastTime": 1609787520,
    "lastResult": true
  },
  "the end-[de.noun.en]-Ende": {
    "priorParams": [
      1.2361418252249252,
      1.0000000000000333,
      2348170.6878349707
    ],
    "numDrills": 7,
    "lastTime": 1609787799,
    "lastResult": true
  },
  "Ende-[de.noun.gender]-das": {
    "priorParams": [
      2.6991130777620227,
      2.381266039739834,
      863843.7204158901
    ],
    "numDrills": 13,
    "lastTime": 1609875045,
    "lastResult": true
  },
  "the million-[de.noun.en]-Million": {
    "priorParams": [
      0.7064007328327208,
      1.0000000000000262,
      2647858.238339239
    ],
    "numDrills": 7,
    "lastTime": 1608756291,
    "lastResult": true
  },
  "Million-[de.noun.gender]-die": {
    "priorParams": [
      1.19861303719577,
      0.9999999999999717,
      2348170.68783497
    ],
    "numDrills": 7,
    "lastTime": 1609787559,
    "lastResult": true
  },
  "the school-[de.noun.en]-Schule": {
    "priorParams": [
      1.2568909498650171,
      0.9999999999999845,
      1623539.4170187458
    ],
    "numDrills": 4,
    "lastTime": 1608756291,
    "lastResult": true
  },
  "Schule-[de.noun.gender]-die": {
    "priorParams": [
      1.1985764129416678,
      1.000000000000006,
      2348170.68783497
    ],
    "numDrills": 7,
    "lastTime": 1609787503,
    "lastResult": true
  },
  "the week-[de.noun.en]-Woche": {
    "priorParams": [
      1.2567067843333088,
      1.0000000000000013,
      1623539.4170187458
    ],
    "numDrills": 4,
    "lastTime": 1608756260,
    "lastResult": true
  },
  "Woche-[de.noun.gender]-die": {
    "priorParams": [
      1.198575135351408,
      1.0000000000000038,
      2348170.68783497
    ],
    "numDrills": 7,
    "lastTime": 1609787524,
    "lastResult": true
  },
  "the father-[de.noun.en]-Vater": {
    "priorParams": [
      0.7965962652078994,
      1.0000000000000067,
      2348170.6878349707
    ],
    "numDrills": 7,
    "lastTime": 1608756275,
    "lastResult": true
  },
  "Vater-[de.noun.gender]-der": {
    "priorParams": [
      1.1985951509321442,
      0.9999999999999907,
      2348170.68783497
    ],
    "numDrills": 7,
    "lastTime": 1609787513,
    "lastResult": true
  },
  "the side-[de.noun.en]-Seite": {
    "priorParams": [
      1.2359382625101658,
      0.9999999999999754,
      2348170.6878349707
    ],
    "numDrills": 7,
    "lastTime": 1609787818,
    "lastResult": true
  },
  "Seite-[de.noun.gender]-die": {
    "priorParams": [
      1.1986006871566124,
      1.000000000000008,
      2348170.68783497
    ],
    "numDrills": 7,
    "lastTime": 1609787557,
    "lastResult": true
  },
  "the page-[de.noun.en]-Seite": {
    "priorParams": [
      1.256760986897826,
      1.0000000000000093,
      1623539.4170187458
    ],
    "numDrills": 4,
    "lastTime": 1608756264,
    "lastResult": true
  },
  "the life-[de.noun.en]-Leben": {
    "priorParams": [
      0.7063678760888291,
      1.0000000000000027,
      2647858.238339239
    ],
    "numDrills": 7,
    "lastTime": 1608756266,
    "lastResult": true
  },
  "Leben-[de.noun.gender]-das": {
    "priorParams": [
      14.32213852544822,
      9.088216994673619,
      148653.91516071517
    ],
    "numDrills": 30,
    "lastTime": 1609787356,
    "lastResult": true
  },
  "the mother-[de.noun.en]-Mutter": {
    "priorParams": [
      1.2021765406743192,
      1.0000000000000053,
      1623539.4170187458
    ],
    "numDrills": 4,
    "lastTime": 1608667906,
    "lastResult": true
  },
  "Mutter-[de.noun.gender]-die": {
    "priorParams": [
      1.1986053716542138,
      0.9999999999999808,
      2348170.68783497
    ],
    "numDrills": 7,
    "lastTime": 1609787551,
    "lastResult": true
  },
  "the grounding/basis/reason-[de.noun.en]-Grund": {
    "priorParams": [
      2.5758742082927144,
      1.7014647058748407,
      863843.7204158901
    ],
    "numDrills": 10,
    "lastTime": 1609276311,
    "lastResult": true
  },
  "Grund-[de.noun.gender]-der": {
    "priorParams": [
      2.1191510344359896,
      2.357863626747328,
      999521.1606876455
    ],
    "numDrills": 17,
    "lastTime": 1609444969,
    "lastResult": true
  },
  "the eye-[de.noun.en]-Auge": {
    "priorParams": [
      1.2569014208149902,
      0.9999999999999865,
      1623539.4170187458
    ],
    "numDrills": 5,
    "lastTime": 1608756243,
    "lastResult": true
  },
  "Auge-[de.noun.gender]-das": {
    "priorParams": [
      1.1985934474784423,
      0.9999999999999922,
      2348170.68783497
    ],
    "numDrills": 7,
    "lastTime": 1609787554,
    "lastResult": true
  },
  "the word-[de.noun.en]-Wort": {
    "priorParams": [
      0.7064403875236167,
      0.9999999999999762,
      2647858.238339239
    ],
    "numDrills": 7,
    "lastTime": 1608756249,
    "lastResult": true
  },
  "Wort-[de.noun.gender]-das": {
    "priorParams": [
      2.1817995636166585,
      2.343761552457655,
      974092.6090214391
    ],
    "numDrills": 12,
    "lastTime": 1609444990,
    "lastResult": true
  },
  "the money-[de.noun.en]-Geld": {
    "priorParams": [
      1.236153323537266,
      1.0000000000000175,
      2348170.6878349707
    ],
    "numDrills": 7,
    "lastTime": 1609787856,
    "lastResult": true
  },
  "Geld-[de.noun.gender]-das": {
    "priorParams": [
      1.1986083526981883,
      0.9999999999999974,
      2348170.68783497
    ],
    "numDrills": 7,
    "lastTime": 1609787556,
    "lastResult": true
  },
  "the thing-[de.noun.en]-Sache": {
    "priorParams": [
      0.6765907028181884,
      1.0188262508671198,
      2716980.20825752
    ],
    "numDrills": 9,
    "lastTime": 1608756268,
    "lastResult": true
  },
  "Sache-[de.noun.gender]-die": {
    "priorParams": [
      2.8964877500320334,
      1.997015051179267,
      766072.9240637763
    ],
    "numDrills": 10,
    "lastTime": 1609529257,
    "lastResult": true
  },
  "the type/kind-[de.noun.en]-Art": {
    "priorParams": [
      0.7743788047398621,
      1.000000000000408,
      2409469.356055713
    ],
    "numDrills": 7,
    "lastTime": 1608755231,
    "lastResult": true
  },
  "Art-[de.noun.gender]-die": {
    "priorParams": [
      3.057610764124222,
      1.7793966985916798,
      886394.2402254909
    ],
    "numDrills": 18,
    "lastTime": 1609875134,
    "lastResult": true
  },
  "the area/region-[de.noun.en]-Bereich": {
    "priorParams": [
      0.6767568925631484,
      1.0183930302746664,
      2716980.20825752
    ],
    "numDrills": 10,
    "lastTime": 1608756281,
    "lastResult": true
  },
  "Bereich-[de.noun.gender]-der": {
    "priorParams": [
      5.62921756457146,
      4.121514963780957,
      404083.23631066456
    ],
    "numDrills": 23,
    "lastTime": 1609836708,
    "lastResult": true
  },
  "the way/path-[de.noun.en]-Weg": {
    "priorParams": [
      1.256783160674223,
      1.000000000000001,
      1623539.4170187458
    ],
    "numDrills": 4,
    "lastTime": 1608756276,
    "lastResult": true
  },
  "Weg-[de.noun.gender]-der": {
    "priorParams": [
      1.1985917440248044,
      0.9999999999999845,
      2348170.68783497
    ],
    "numDrills": 7,
    "lastTime": 1609787548,
    "lastResult": true
  },
  "the hour-[de.noun.en]-Stunde": {
    "priorParams": [
      1.2359574263640414,
      1.0000000000000253,
      2348170.6878349707
    ],
    "numDrills": 7,
    "lastTime": 1609787866,
    "lastResult": true
  },
  "Stunde-[de.noun.gender]-die": {
    "priorParams": [
      1.1985810974392952,
      1.0000000000000129,
      2348170.68783497
    ],
    "numDrills": 7,
    "lastTime": 1609787529,
    "lastResult": true
  },
  "the name-[de.noun.en]-Name": {
    "priorParams": [
      0.7064713559489015,
      1.0000000000000022,
      2647858.238339239
    ],
    "numDrills": 7,
    "lastTime": 1608756290,
    "lastResult": true
  },
  "Name-[de.noun.gender]-der": {
    "priorParams": [
      1.1318896082680174,
      0.9999999999999928,
      2348170.68783497
    ],
    "numDrills": 7,
    "lastTime": 1609631230,
    "lastResult": true
  },
  "the history-[de.noun.en]-Geschichte": {
    "priorParams": [
      2.571511688893854,
      1.7228405998566156,
      863843.7204158901
    ],
    "numDrills": 10,
    "lastTime": 1609276241,
    "lastResult": true
  },
  "Geschichte-[de.noun.gender]-die": {
    "priorParams": [
      2.896198354461635,
      1.9971381973044826,
      766072.9240637763
    ],
    "numDrills": 10,
    "lastTime": 1609529224,
    "lastResult": true
  },
  "the society/company-[de.noun.en]-Gesellschaft": {
    "priorParams": [
      1.2019757448103066,
      1.0000000000000087,
      1623539.4170187458
    ],
    "numDrills": 4,
    "lastTime": 1608667864,
    "lastResult": true
  },
  "Gesellschaft-[de.noun.gender]-die": {
    "priorParams": [
      5.233523977041549,
      2.9779071834429494,
      404083.2363106646
    ],
    "numDrills": 14,
    "lastTime": 1609444943,
    "lastResult": true
  },
  "the head-[de.noun.en]-Kopf": {
    "priorParams": [
      1.2021457437626588,
      1.000000000000004,
      1623539.4170187458
    ],
    "numDrills": 4,
    "lastTime": 1608667873,
    "lastResult": true
  },
  "Kopf-[de.noun.gender]-der": {
    "priorParams": [
      1.1318866272240882,
      1.0000000000000353,
      2348170.68783497
    ],
    "numDrills": 7,
    "lastTime": 1609631239,
    "lastResult": true
  },
  "the pair/couple-[de.noun.en]-Paar": {
    "priorParams": [
      0.7064505844441518,
      1.0000000000000153,
      2647858.238339239
    ],
    "numDrills": 7,
    "lastTime": 1608756292,
    "lastResult": true
  },
  "Paar-[de.noun.gender]-das": {
    "priorParams": [
      0.7592706140301273,
      0.9999999999999905,
      2348170.68783497
    ],
    "numDrills": 7,
    "lastTime": 1608756254,
    "lastResult": true
  },
  "the likelihood/possibility-[de.noun.en]-M\u00f6glichkeit": {
    "priorParams": [
      0.6764518318475563,
      1.019248700569921,
      2716980.20825752
    ],
    "numDrills": 9,
    "lastTime": 1608756267,
    "lastResult": true
  },
  "M\u00f6glichkeit-[de.noun.gender]-die": {
    "priorParams": [
      1.1318917375851123,
      0.9999999999999843,
      2348170.68783497
    ],
    "numDrills": 7,
    "lastTime": 1609631227,
    "lastResult": true
  },
  "the enterprise/company-[de.noun.en]-Unternehmen": {
    "priorParams": [
      0.7747365598570148,
      1.0000000000153233,
      2409469.356055713
    ],
    "numDrills": 7,
    "lastTime": 1608755318,
    "lastResult": true
  },
  "Unternehmen-[de.noun.gender]-das": {
    "priorParams": [
      4.9880903524966165,
      4.092050519260452,
      414631.77282229665
    ],
    "numDrills": 22,
    "lastTime": 1609787477,
    "lastResult": true
  },
  "the picture-[de.noun.en]-Bild": {
    "priorParams": [
      1.2361482131762467,
      1.000000000000049,
      2348170.6878349707
    ],
    "numDrills": 7,
    "lastTime": 1609787801,
    "lastResult": true
  },
  "Bild-[de.noun.gender]-das": {
    "priorParams": [
      1.131890459994891,
      1.0000000000000249,
      2348170.68783497
    ],
    "numDrills": 7,
    "lastTime": 1609631244,
    "lastResult": true
  },
  "the book-[de.noun.en]-Buch": {
    "priorParams": [
      1.2568453704357827,
      1.0000000000000115,
      1623539.4170187458
    ],
    "numDrills": 4,
    "lastTime": 1608756258,
    "lastResult": true
  },
  "Buch-[de.noun.gender]-das": {
    "priorParams": [
      0.7588247350293273,
      1.0000000000000102,
      2348170.68783497
    ],
    "numDrills": 7,
    "lastTime": 1608755218,
    "lastResult": true
  },
  "the water-[de.noun.en]-Wasser": {
    "priorParams": [
      1.2569137395796526,
      1.000000000000004,
      1623539.4170187458
    ],
    "numDrills": 4,
    "lastTime": 1608756301,
    "lastResult": true
  },
  "Wasser-[de.noun.gender]-das": {
    "priorParams": [
      0.7588183470780191,
      0.9999999999999626,
      2348170.68783497
    ],
    "numDrills": 7,
    "lastTime": 1608755209,
    "lastResult": true
  },
  "the place-[de.noun.en]-Stelle": {
    "priorParams": [
      1.0963404150445684,
      1.0000000000000029,
      2647858.238339239
    ],
    "numDrills": 7,
    "lastTime": 1609787870,
    "lastResult": true
  },
  "Stelle-[de.noun.gender]-die": {
    "priorParams": [
      1.8739824828739233,
      0.9999999999999791,
      863843.7204158901
    ],
    "numDrills": 7,
    "lastTime": 1608667945,
    "lastResult": true
  },
  "the form/shape-[de.noun.en]-Form": {
    "priorParams": [
      1.0963630748679352,
      1.000000000000016,
      2647858.238339239
    ],
    "numDrills": 7,
    "lastTime": 1609787862,
    "lastResult": true
  },
  "Form-[de.noun.gender]-die": {
    "priorParams": [
      2.6031712071009268,
      2.032979674055358,
      863843.7204158901
    ],
    "numDrills": 11,
    "lastTime": 1609529278,
    "lastResult": true
  },
  "the mark (currency)-[de.noun.en]-Mark": {
    "priorParams": [
      0.7064619143558354,
      1.0000000000000364,
      2647858.238339239
    ],
    "numDrills": 7,
    "lastTime": 1608756282,
    "lastResult": true
  },
  "Mark-[de.noun.gender]-die": {
    "priorParams": [
      0.9087175594539204,
      0.9999999999999963,
      3063737.4297830197
    ],
    "numDrills": 11,
    "lastTime": 1609836727,
    "lastResult": true
  },
  "the development-[de.noun.en]-Entwicklung": {
    "priorParams": [
      2.5492804970423215,
      1.7045680509967813,
      863843.7204158901
    ],
    "numDrills": 10,
    "lastTime": 1609276235,
    "lastResult": true
  },
  "Entwicklung-[de.noun.gender]-die": {
    "priorParams": [
      1.873985955724266,
      0.9999999999999801,
      863843.7204158901
    ],
    "numDrills": 6,
    "lastTime": 1608667950,
    "lastResult": true
  },
  "the month-[de.noun.en]-Monat": {
    "priorParams": [
      0.7064313235942814,
      1.00000000000002,
      2647858.238339239
    ],
    "numDrills": 7,
    "lastTime": 1608756296,
    "lastResult": true
  },
  "Monat-[de.noun.gender]-der": {
    "priorParams": [
      0.9087156010615125,
      1.0000000000000504,
      3063737.4297830197
    ],
    "numDrills": 11,
    "lastTime": 1609836729,
    "lastResult": true
  },
  "the family-[de.noun.en]-Familie": {
    "priorParams": [
      1.256911891764954,
      1.000000000000003,
      1623539.4170187458
    ],
    "numDrills": 4,
    "lastTime": 1608756277,
    "lastResult": true
  },
  "Familie-[de.noun.gender]-die": {
    "priorParams": [
      1.8739732219395315,
      1.0000000000000338,
      863843.7204158901
    ],
    "numDrills": 6,
    "lastTime": 1608667927,
    "lastResult": true
  },
  "the morning-[de.noun.en]-Morgen": {
    "priorParams": [
      1.256701856827436,
      1.0000000000000029,
      1623539.4170187458
    ],
    "numDrills": 4,
    "lastTime": 1608756279,
    "lastResult": true
  },
  "Morgen-[de.noun.gender]-der": {
    "priorParams": [
      1.8738377807743702,
      0.9999999999999998,
      863843.7204158901
    ],
    "numDrills": 6,
    "lastTime": 1608667848,
    "lastResult": true
  },
  "the evening-[de.noun.en]-Abend": {
    "priorParams": [
      0.7063977115229364,
      1.0000000000000162,
      2647858.238339239
    ],
    "numDrills": 7,
    "lastTime": 1608756293,
    "lastResult": true
  },
  "Abend-[de.noun.gender]-der": {
    "priorParams": [
      1.8739408086692608,
      0.9999999999999712,
      863843.7204158901
    ],
    "numDrills": 6,
    "lastTime": 1608667919,
    "lastResult": true
  },
  "the task/asg./job-[de.noun.en]-Aufgabe": {
    "priorParams": [
      1.2047025033685426,
      0.9999999999999717,
      1623539.4170187458
    ],
    "numDrills": 4,
    "lastTime": 1608671893,
    "lastResult": true
  },
  "Aufgabe-[de.noun.gender]-die": {
    "priorParams": [
      1.8739674338555439,
      0.999999999999985,
      863843.7204158901
    ],
    "numDrills": 6,
    "lastTime": 1608667958,
    "lastResult": true
  },
  "the university-[de.noun.en]-Universit\u00e4t": {
    "priorParams": [
      1.2567757694154271,
      1.000000000000007,
      1623539.4170187458
    ],
    "numDrills": 4,
    "lastTime": 1608756260,
    "lastResult": true
  },
  "Universit\u00e4t-[de.noun.gender]-die": {
    "priorParams": [
      1.8739639610051715,
      1.000000000000002,
      863843.7204158901
    ],
    "numDrills": 6,
    "lastTime": 1608667941,
    "lastResult": true
  },
  "the sense/meaning-[de.noun.en]-Sinn": {
    "priorParams": [
      1.6690745339795703,
      2.0256304313188593,
      1098412.1184482018
    ],
    "numDrills": 9,
    "lastTime": 1609361658,
    "lastResult": true
  },
  "Sinn-[de.noun.gender]-der": {
    "priorParams": [
      0.9087093994856986,
      0.9999999999999459,
      3063737.4297830197
    ],
    "numDrills": 11,
    "lastTime": 1609836720,
    "lastResult": true
  },
  "the state-[de.noun.en]-Staat": {
    "priorParams": [
      1.2567443565655394,
      1.0000000000000069,
      1623539.4170187458
    ],
    "numDrills": 4,
    "lastTime": 1608756266,
    "lastResult": true
  },
  "Staat-[de.noun.gender]-der": {
    "priorParams": [
      1.6183168295206878,
      3.12991003268202,
      1127086.0135646083
    ],
    "numDrills": 18,
    "lastTime": 1609787786,
    "lastResult": true
  },
  "the goal-[de.noun.en]-Ziel": {
    "priorParams": [
      0.774475921560059,
      0.999999999996403,
      2409469.356055713
    ],
    "numDrills": 7,
    "lastTime": 1608755281,
    "lastResult": true
  },
  "Ziel-[de.noun.gender]-das": {
    "priorParams": [
      6.513160204050918,
      4.659659312644003,
      367703.2860328025
    ],
    "numDrills": 29,
    "lastTime": 1609811570,
    "lastResult": true
  },
  "the destination-[de.noun.en]-Ziel": {
    "priorParams": [
      0.7746103910013972,
      0.9999999999996272,
      2409469.356055713
    ],
    "numDrills": 7,
    "lastTime": 1608755272,
    "lastResult": true
  },
  "the friend (m)-[de.noun.en]-Freund": {
    "priorParams": [
      1.2568810948532911,
      0.9999999999999816,
      1623539.4170187458
    ],
    "numDrills": 4,
    "lastTime": 1608756286,
    "lastResult": true
  },
  "Freund-[de.noun.gender]-der": {
    "priorParams": [
      1.873928074884463,
      0.9999999999999912,
      863843.7204158901
    ],
    "numDrills": 6,
    "lastTime": 1608667956,
    "lastResult": true
  },
  "the friend (f)-[de.noun.en]-Freundin": {
    "priorParams": [
      0.7965826375784628,
      0.9999999999999858,
      2348170.6878349707
    ],
    "numDrills": 7,
    "lastTime": 1608756240,
    "lastResult": true
  },
  "Freundin-[de.noun.gender]-die": {
    "priorParams": [
      1.873947754369996,
      1.0000000000000009,
      863843.7204158901
    ],
    "numDrills": 6,
    "lastTime": 1608667953,
    "lastResult": true
  },
  "the topic/theme-[de.noun.en]-Thema": {
    "priorParams": [
      0.7063962008680459,
      1.0000000000000067,
      2647858.238339239
    ],
    "numDrills": 7,
    "lastTime": 1608756295,
    "lastResult": true
  },
  "Thema-[de.noun.gender]-das": {
    "priorParams": [
      1.873893346380577,
      0.9999999999999818,
      863843.7204158901
    ],
    "numDrills": 6,
    "lastTime": 1608667924,
    "lastResult": true
  },
  "the person-[de.noun.en]-Person": {
    "priorParams": [
      1.2568656963974538,
      0.9999999999999769,
      1623539.4170187458
    ],
    "numDrills": 4,
    "lastTime": 1608756209,
    "lastResult": true
  },
  "Person-[de.noun.gender]-die": {
    "priorParams": [
      0.8058482088731176,
      1.0000000000000169,
      3454749.876397994
    ],
    "numDrills": 12,
    "lastTime": 1609836707,
    "lastResult": true
  },
  "the euro (currency)-[de.noun.en]-Euro": {
    "priorParams": [
      0.7966239463301943,
      1.0000000000000355,
      2348170.6878349707
    ],
    "numDrills": 7,
    "lastTime": 1608756265,
    "lastResult": true
  },
  "Euro-[de.noun.gender]-der": {
    "priorParams": [
      1.8657962702836595,
      3.486651235521854,
      1127086.0135646083
    ],
    "numDrills": 24,
    "lastTime": 1609874841,
    "lastResult": true
  },
  "the night-[de.noun.en]-Nacht": {
    "priorParams": [
      1.2568681601504044,
      1.00000000000002,
      1623539.4170187458
    ],
    "numDrills": 4,
    "lastTime": 1608756298,
    "lastResult": true
  },
  "Nacht-[de.noun.gender]-die": {
    "priorParams": [
      1.067175334043675,
      1.0000000000000002,
      2647858.238339239
    ],
    "numDrills": 7,
    "lastTime": 1609874926,
    "lastResult": true
  },
  "the thing-[de.noun.en]-Ding": {
    "priorParams": [
      1.2568552254475016,
      1.0000000000000064,
      1623539.4170187458
    ],
    "numDrills": 4,
    "lastTime": 1608756257,
    "lastResult": true
  },
  "Ding-[de.noun.gender]-das": {
    "priorParams": [
      1.8739211291837046,
      1.000000000000034,
      863843.7204158901
    ],
    "numDrills": 6,
    "lastTime": 1608667961,
    "lastResult": true
  },
  "the room/space-[de.noun.en]-Raum": {
    "priorParams": [
      0.7966009497055208,
      0.9999999999999845,
      2348170.6878349707
    ],
    "numDrills": 7,
    "lastTime": 1608756281,
    "lastResult": true
  },
  "Raum-[de.noun.gender]-der": {
    "priorParams": [
      1.9407861505598407,
      1.9959714691906625,
      1127086.0135646083
    ],
    "numDrills": 18,
    "lastTime": 1609529241,
    "lastResult": true
  },
  "the look/glance/view-[de.noun.en]-Blick": {
    "priorParams": [
      0.7744236278858134,
      1.000000000006567,
      2409469.356055713
    ],
    "numDrills": 7,
    "lastTime": 1608755244,
    "lastResult": true
  },
  "Blick-[de.noun.gender]-der": {
    "priorParams": [
      0.8058444459379083,
      0.9999999999999958,
      3454749.876397994
    ],
    "numDrills": 11,
    "lastTime": 1609836723,
    "lastResult": true
  },
  "the place-[de.noun.en]-Platz": {
    "priorParams": [
      0.7746083158540852,
      1.0000000000066525,
      2409469.356055713
    ],
    "numDrills": 7,
    "lastTime": 1608755274,
    "lastResult": true
  },
  "Platz-[de.noun.gender]-der": {
    "priorParams": [
      0.8058484983297013,
      0.9999999999999346,
      3454749.876397994
    ],
    "numDrills": 11,
    "lastTime": 1609836725,
    "lastResult": true
  },
  "the public square-[de.noun.en]-Platz": {
    "priorParams": [
      1.2362125185526363,
      1.0000000000000135,
      2348170.6878349707
    ],
    "numDrills": 7,
    "lastTime": 1609787853,
    "lastResult": true
  },
  "the number-[de.noun.en]-Zahl": {
    "priorParams": [
      2.5721439151053764,
      1.720100102540555,
      863843.7204158901
    ],
    "numDrills": 10,
    "lastTime": 1609276290,
    "lastResult": true
  },
  "Zahl-[de.noun.gender]-die": {
    "priorParams": [
      1.8738447264751894,
      0.9999999999999843,
      863843.7204158901
    ],
    "numDrills": 6,
    "lastTime": 1608667904,
    "lastResult": true
  },
  "the system-[de.noun.en]-System": {
    "priorParams": [
      0.7063776953456282,
      1.0000000000000269,
      2647858.238339239
    ],
    "numDrills": 7,
    "lastTime": 1608756255,
    "lastResult": true
  },
  "System-[de.noun.gender]-das": {
    "priorParams": [
      0.805842998655131,
      0.9999999999999687,
      3454749.876397994
    ],
    "numDrills": 12,
    "lastTime": 1609836731,
    "lastResult": true
  },
  "the clock/watch-[de.noun.en]-Uhr": {
    "priorParams": [
      1.2359463539151179,
      0.9999999999999942,
      2348170.6878349707
    ],
    "numDrills": 7,
    "lastTime": 1609787811,
    "lastResult": true
  },
  "Uhr-[de.noun.gender]-die": {
    "priorParams": [
      1.0671742010525156,
      0.9999999999999867,
      2647858.238339239
    ],
    "numDrills": 7,
    "lastTime": 1609874941,
    "lastResult": true
  },
  "the parents-[de.noun.en]-Eltern": {
    "priorParams": [
      0.7064505844441523,
      1.0000000000000138,
      2647858.238339239
    ],
    "numDrills": 7,
    "lastTime": 1608756302,
    "lastResult": true
  },
  "Eltern-[de.noun.gender]-plu": {
    "priorParams": [
      1.8736757144229244,
      0.9999999999999948,
      863843.7204158901
    ],
    "numDrills": 6,
    "lastTime": 1608667774,
    "lastResult": true
  },
  "the street-[de.noun.en]-Stra\u00dfe": {
    "priorParams": [
      1.256720950912687,
      1.0000000000000118,
      1623539.4170187458
    ],
    "numDrills": 4,
    "lastTime": 1608756253,
    "lastResult": true
  },
  "Stra\u00dfe-[de.noun.gender]-die": {
    "priorParams": [
      1.8738736668950837,
      1.000000000000016,
      863843.7204158901
    ],
    "numDrills": 6,
    "lastTime": 1608667947,
    "lastResult": true
  },
  "the minute-[de.noun.en]-Minute": {
    "priorParams": [
      0.7064305682668226,
      0.9999999999999987,
      2647858.238339239
    ],
    "numDrills": 7,
    "lastTime": 1608756252,
    "lastResult": true
  },
  "Minute-[de.noun.gender]-die": {
    "priorParams": [
      1.8737764270841957,
      0.9999999999999873,
      863843.7204158901
    ],
    "numDrills": 6,
    "lastTime": 1608667851,
    "lastResult": true
  },
  "the group-[de.noun.en]-Gruppe": {
    "priorParams": [
      1.2567806969212838,
      0.999999999999996,
      1623539.4170187458
    ],
    "numDrills": 4,
    "lastTime": 1608756276,
    "lastResult": true
  },
  "Gruppe-[de.noun.gender]-die": {
    "priorParams": [
      1.0671760893711524,
      0.9999999999999958,
      2647858.238339239
    ],
    "numDrills": 7,
    "lastTime": 1609874938,
    "lastResult": true
  },
  "the value/worth-[de.noun.en]-Wert": {
    "priorParams": [
      0.7064256586384356,
      0.9999999999999996,
      2647858.238339239
    ],
    "numDrills": 7,
    "lastTime": 1608756284,
    "lastResult": true
  },
  "Wert-[de.noun.gender]-der": {
    "priorParams": [
      4.330446794675152,
      4.8773840284097645,
      358348.6446560392
    ],
    "numDrills": 16,
    "lastTime": 1609788040,
    "lastResult": true
  },
  "the face-[de.noun.en]-Gesicht": {
    "priorParams": [
      2.589350789950623,
      1.9982447009489692,
      766072.9240637764
    ],
    "numDrills": 9,
    "lastTime": 1609361624,
    "lastResult": true
  },
  "Gesicht-[de.noun.gender]-das": {
    "priorParams": [
      1.0671522965565883,
      1.0000000000000298,
      2647858.238339239
    ],
    "numDrills": 7,
    "lastTime": 1609874934,
    "lastResult": true
  },
  "the language-[de.noun.en]-Sprache": {
    "priorParams": [
      2.959647040352587,
      2.0306780447638464,
      863843.7204158901
    ],
    "numDrills": 12,
    "lastTime": 1609788072,
    "lastResult": true
  },
  "Sprache-[de.noun.gender]-die": {
    "priorParams": [
      1.0671534295477465,
      1.000000000000052,
      2647858.238339239
    ],
    "numDrills": 7,
    "lastTime": 1609874950,
    "lastResult": true
  },
  "the beginning-[de.noun.en]-Anfang": {
    "priorParams": [
      0.774469281090903,
      1.000000000008935,
      2409469.356055713
    ],
    "numDrills": 7,
    "lastTime": 1608755288,
    "lastResult": true
  },
  "Anfang-[de.noun.gender]-der": {
    "priorParams": [
      6.066168946481793,
      3.175868083020507,
      367703.2860328025
    ],
    "numDrills": 20,
    "lastTime": 1609787526,
    "lastResult": true
  },
  "the place/location-[de.noun.en]-Ort": {
    "priorParams": [
      0.6811738982766065,
      1.0000000000012956,
      2716980.20825752
    ],
    "numDrills": 8,
    "lastTime": 1608756251,
    "lastResult": true
  },
  "Ort-[de.noun.gender]-der": {
    "priorParams": [
      2.6023813079469353,
      2.0365068870175214,
      863843.7204158901
    ],
    "numDrills": 11,
    "lastTime": 1609529250,
    "lastResult": true
  },
  "the town-[de.noun.en]-Ort": {
    "priorParams": [
      2.509197208393256,
      1.7074562073117834,
      886394.2402254909
    ],
    "numDrills": 12,
    "lastTime": 1609618658,
    "lastResult": true
  },
  "the moment-[de.noun.en]-Moment": {
    "priorParams": [
      1.2362120926892544,
      1.0000000000000304,
      2348170.6878349707
    ],
    "numDrills": 7,
    "lastTime": 1609787859,
    "lastResult": true
  },
  "Moment-[de.noun.gender]-der": {
    "priorParams": [
      3.21043299124443,
      6.986545521330363,
      594508.1070686124
    ],
    "numDrills": 32,
    "lastTime": 1609875033,
    "lastResult": true
  },
  "the result/consequence-[de.noun.en]-Folge": {
    "priorParams": [
      1.256927906159007,
      0.9999999999999791,
      1623539.4170187458
    ],
    "numDrills": 4,
    "lastTime": 1608756294,
    "lastResult": true
  },
  "Folge-[de.noun.gender]-die": {
    "priorParams": [
      1.0671632488045675,
      0.9999999999999574,
      2647858.238339239
    ],
    "numDrills": 7,
    "lastTime": 1609874930,
    "lastResult": true
  },
  "the interest-[de.noun.en]-Interesse": {
    "priorParams": [
      0.7064286799482185,
      1.0000000000000062,
      2647858.238339239
    ],
    "numDrills": 7,
    "lastTime": 1608756280,
    "lastResult": true
  },
  "Interesse-[de.noun.gender]-das": {
    "priorParams": [
      5.6207480653697095,
      3.2367657818912337,
      367703.2860328025
    ],
    "numDrills": 22,
    "lastTime": 1609529259,
    "lastResult": true
  },
  "the billion-[de.noun.en]-Milliarde": {
    "priorParams": [
      0.7744281932076245,
      1.0000000000011564,
      2409469.356055713
    ],
    "numDrills": 7,
    "lastTime": 1608755247,
    "lastResult": true
  },
  "Milliarde-[de.noun.gender]-die": {
    "priorParams": [
      1.0671481422556544,
      0.9999999999999787,
      2647858.238339239
    ],
    "numDrills": 7,
    "lastTime": 1609874931,
    "lastResult": true
  },
  "the role-[de.noun.en]-Rolle": {
    "priorParams": [
      0.7744281932073961,
      1.0000000000020792,
      2409469.356055713
    ],
    "numDrills": 7,
    "lastTime": 1608755241,
    "lastResult": true
  },
  "Rolle-[de.noun.gender]-die": {
    "priorParams": [
      1.0671587168398822,
      0.999999999999968,
      2647858.238339239
    ],
    "numDrills": 7,
    "lastTime": 1609874943,
    "lastResult": true
  },
  "the roll-[de.noun.en]-Rolle": {
    "priorParams": [
      0.7744593203937824,
      0.9999999999990368,
      2409469.356055713
    ],
    "numDrills": 7,
    "lastTime": 1608755278,
    "lastResult": true
  },
  "the door-[de.noun.en]-T\u00fcr": {
    "priorParams": [
      0.7064653133293367,
      1.0000000000000095,
      2647858.238339239
    ],
    "numDrills": 7,
    "lastTime": 1608756263,
    "lastResult": true
  },
  "T\u00fcr-[de.noun.gender]-die": {
    "priorParams": [
      1.8738076827376593,
      1.0000000000000167,
      863843.7204158901
    ],
    "numDrills": 6,
    "lastTime": 1608667926,
    "lastResult": true
  },
  "the pupil/student (m)-[de.noun.en]-Sch\u00fcler": {
    "priorParams": [
      0.7063750516995678,
      1.000000000000018,
      2647858.238339239
    ],
    "numDrills": 7,
    "lastTime": 1608756270,
    "lastResult": true
  },
  "Sch\u00fcler-[de.noun.gender]-der": {
    "priorParams": [
      1.8736213064335228,
      1.0000000000000406,
      863843.7204158901
    ],
    "numDrills": 6,
    "lastTime": 1608667772,
    "lastResult": true
  },
  "the meaning-[de.noun.en]-Bedeutung": {
    "priorParams": [
      1.0963864900187688,
      1.0000000000000229,
      2647858.238339239
    ],
    "numDrills": 7,
    "lastTime": 1609787881,
    "lastResult": true
  },
  "Bedeutung-[de.noun.gender]-die": {
    "priorParams": [
      1.067164381795723,
      0.9999999999999742,
      2647858.238339239
    ],
    "numDrills": 7,
    "lastTime": 1609874945,
    "lastResult": true
  },
  "the significance-[de.noun.en]-Bedeutung": {
    "priorParams": [
      0.7965937100273841,
      1.0000000000000346,
      2348170.6878349707
    ],
    "numDrills": 7,
    "lastTime": 1608756217,
    "lastResult": true
  },
  "the text-[de.noun.en]-Text": {
    "priorParams": [
      1.204668010827482,
      0.9999999999999856,
      1623539.4170187458
    ],
    "numDrills": 4,
    "lastTime": 1608671882,
    "lastResult": true
  },
  "Text-[de.noun.gender]-der": {
    "priorParams": [
      0.7146052151710461,
      1.0000000000000526,
      3895665.6639199127
    ],
    "numDrills": 12,
    "lastTime": 1609836703,
    "lastResult": true
  },
  "the result-[de.noun.en]-Ergebnis": {
    "priorParams": [
      0.7744356637325998,
      0.9999999999993757,
      2409469.356055713
    ],
    "numDrills": 7,
    "lastTime": 1608755227,
    "lastResult": true
  },
  "Ergebnis-[de.noun.gender]-das": {
    "priorParams": [
      4.66719458888852,
      2.5618730684707005,
      527221.0160217481
    ],
    "numDrills": 20,
    "lastTime": 1609787413,
    "lastResult": true
  },
  "the war-[de.noun.en]-Krieg": {
    "priorParams": [
      3.4035069090976564,
      3.194518515064211,
      673493.5219002627
    ],
    "numDrills": 11,
    "lastTime": 1609631236,
    "lastResult": true
  },
  "Krieg-[de.noun.gender]-der": {
    "priorParams": [
      1.0671602274947685,
      1.0000000000000393,
      2647858.238339239
    ],
    "numDrills": 7,
    "lastTime": 1609874927,
    "lastResult": true
  },
  "the way/manner-[de.noun.en]-Weise": {
    "priorParams": [
      0.7744825620240651,
      1.0000000000063212,
      2409469.356055713
    ],
    "numDrills": 7,
    "lastTime": 1608755284,
    "lastResult": true
  },
  "Weise-[de.noun.gender]-die": {
    "priorParams": [
      1.067153807211461,
      1.0000000000000089,
      2647858.238339239
    ],
    "numDrills": 7,
    "lastTime": 1609874948,
    "lastResult": true
  },
  "the rule/government-[de.noun.en]-Regierung": {
    "priorParams": [
      0.7743783897131006,
      0.9999999999906961,
      2409469.356055713
    ],
    "numDrills": 7,
    "lastTime": 1608755236,
    "lastResult": true
  },
  "Regierung-[de.noun.gender]-die": {
    "priorParams": [
      1.067145498609579,
      0.9999999999999586,
      2647858.238339239
    ],
    "numDrills": 7,
    "lastTime": 1609874936,
    "lastResult": true
  },
  "the piece/bit/part-[de.noun.en]-St\u00fcck": {
    "priorParams": [
      1.592795045082633,
      3.0320839181549615,
      999521.1606876453
    ],
    "numDrills": 11,
    "lastTime": 1609874804,
    "lastResult": true
  },
  "St\u00fcck-[de.noun.gender]-das": {
    "priorParams": [
      4.301768742285921,
      8.149450274898594,
      353609.21136191546
    ],
    "numDrills": 31,
    "lastTime": 1609787410,
    "lastResult": true
  },
  "the apartment-[de.noun.en]-Wohnung": {
    "priorParams": [
      0.7063705197348921,
      0.999999999999973,
      2647858.238339239
    ],
    "numDrills": 7,
    "lastTime": 1608756250,
    "lastResult": true
  },
  "Wohnung-[de.noun.gender]-die": {
    "priorParams": [
      1.873583105079236,
      0.9999999999999787,
      863843.7204158901
    ],
    "numDrills": 6,
    "lastTime": 1608667791,
    "lastResult": true
  },
  "the conversation-[de.noun.en]-Gespr\u00e4ch": {
    "priorParams": [
      0.7746581193545609,
      0.9999999999919329,
      2409469.356055713
    ],
    "numDrills": 8,
    "lastTime": 1608756253,
    "lastResult": true
  },
  "Gespr\u00e4ch-[de.noun.gender]-das": {
    "priorParams": [
      2.12757119967839,
      4.288702633535381,
      863843.7204158901
    ],
    "numDrills": 18,
    "lastTime": 1609836701,
    "lastResult": true
  },
  "the o'clock-[de.noun.en]-Uhr": {
    "priorParams": [
      0.706266662211096,
      0.9999999999999933,
      2647858.238339239
    ],
    "numDrills": 7,
    "lastTime": 1608756283,
    "lastResult": true
  },
  "the pupil/student (f)-[de.noun.en]-Sch\u00fclerin": {
    "priorParams": [
      0.706253821644522,
      1.0,
      2647858.238339239
    ],
    "numDrills": 7,
    "lastTime": 1608756261,
    "lastResult": true
  },
  "Sch\u00fclerin-[de.noun.gender]-die": {
    "priorParams": [
      1.8737555899818539,
      1.000000000000029,
      863843.7204158901
    ],
    "numDrills": 6,
    "lastTime": 1608667916,
    "lastResult": true
  },
  "the position/role-[de.noun.en]-Stelle": {
    "priorParams": [
      1.9898217228140151,
      0.99999999999999,
      863843.7204158901
    ],
    "numDrills": 6,
    "lastTime": 1609276221,
    "lastResult": true
  }
}