{
  "the year-[de.noun.en]-Jahr": {
    "priorParams": [
      0.7217453347401362,
      0.9999999999999978,
      1623539.4170187458
    ],
    "numDrills": 4,
    "lastTime": 1607856665
  },
  "Jahr-[de.noun.gender]-das": {
    "priorParams": [
      0.9272544722198116,
      1.2959993288986904,
      863843.7204158901
    ],
    "numDrills": 8,
    "lastTime": 1607895459
  },
  "the time/occurrence-[de.noun.en]-Mal": {
    "priorParams": [
      1.0634026793148645,
      0.9999999999999999,
      766072.9240637763
    ],
    "numDrills": 5,
    "lastTime": 1607668679
  },
  "Mal-[de.noun.gender]-das": {
    "priorParams": [
      5.913417459639812,
      5.035251261858023,
      135270.47938265037
    ],
    "numDrills": 16,
    "lastTime": 1608151377
  },
  "the example-[de.noun.en]-Beispiel": {
    "priorParams": [
      1.0633413274532888,
      0.9999999999999988,
      766072.9240637763
    ],
    "numDrills": 5,
    "lastTime": 1607668672
  },
  "Beispiel-[de.noun.gender]-das": {
    "priorParams": [
      2.7203353102329926,
      3.6669027854317853,
      367703.28603280237
    ],
    "numDrills": 19,
    "lastTime": 1608237434,
    "lastResult": true
  },
  "the time-[de.noun.en]-Zeit": {
    "priorParams": [
      0.7217902982311639,
      1.0000000000000009,
      1623539.4170187458
    ],
    "numDrills": 4,
    "lastTime": 1607856698
  },
  "Zeit-[de.noun.gender]-die": {
    "priorParams": [
      0.9080284371753757,
      0.9999999999999813,
      766072.9240637763
    ],
    "numDrills": 5,
    "lastTime": 1607668530
  },
  "the woman/wife-[de.noun.en]-Frau": {
    "priorParams": [
      0.721768740392995,
      1.0000000000000064,
      1623539.4170187458
    ],
    "numDrills": 4,
    "lastTime": 1607856681
  },
  "Frau-[de.noun.gender]-die": {
    "priorParams": [
      0.9080506282742522,
      0.9999999999999808,
      766072.9240637763
    ],
    "numDrills": 5,
    "lastTime": 1607668544
  },
  "the man/human-[de.noun.en]-Mensch": {
    "priorParams": [
      1.0247774477641949,
      1.3121349118272625,
      863843.7204158901
    ],
    "numDrills": 7,
    "lastTime": 1607856669
  },
  "Mensch-[de.noun.gender]-der": {
    "priorParams": [
      0.9080871783194483,
      1.0000000000000273,
      766072.9240637763
    ],
    "numDrills": 5,
    "lastTime": 1607668551
  },
  "the child-[de.noun.en]-Kind": {
    "priorParams": [
      1.168695188886652,
      0.9999999999999981,
      863843.7204158901
    ],
    "numDrills": 6,
    "lastTime": 1607895334
  },
  "Kind-[de.noun.gender]-das": {
    "priorParams": [
      0.9080375746866713,
      1.0000000000000067,
      766072.9240637763
    ],
    "numDrills": 5,
    "lastTime": 1607668539
  },
  "the day-[de.noun.en]-Tag": {
    "priorParams": [
      0.7026450901295404,
      0.9999999999999857,
      1623539.4170187458
    ],
    "numDrills": 3,
    "lastTime": 1607856599
  },
  "Tag-[de.noun.gender]-der": {
    "priorParams": [
      0.9080597657855468,
      1.000000000000015,
      766072.9240637763
    ],
    "numDrills": 5,
    "lastTime": 1607668535
  },
  "the man/husband-[de.noun.en]-Mann": {
    "priorParams": [
      0.7028046181319287,
      0.9999999999999917,
      1623539.4170187458
    ],
    "numDrills": 4,
    "lastTime": 1607856641
  },
  "Mann-[de.noun.gender]-der": {
    "priorParams": [
      0.9080950104719807,
      0.9999999999999921,
      766072.9240637763
    ],
    "numDrills": 5,
    "lastTime": 1607668560
  },
  "the land/country-[de.noun.en]-Land": {
    "priorParams": [
      1.1687403359416952,
      0.9999999999999918,
      863843.7204158901
    ],
    "numDrills": 6,
    "lastTime": 1607895323
  },
  "Land-[de.noun.gender]-das": {
    "priorParams": [
      2.762309836668658,
      4.414742458101715,
      317790.34512605733
    ],
    "numDrills": 17,
    "lastTime": 1608236655
  },
  "the question-[de.noun.en]-Frage": {
    "priorParams": [
      1.1687229716897651,
      1.0000000000000033,
      863843.7204158901
    ],
    "numDrills": 6,
    "lastTime": 1607895330
  },
  "Frage-[de.noun.gender]-die": {
    "priorParams": [
      0.9080310478928758,
      0.9999999999999915,
      766072.9240637763
    ],
    "numDrills": 5,
    "lastTime": 1607668549
  },
  "the house/home-[de.noun.en]-Haus": {
    "priorParams": [
      0.7026284597972531,
      1.0000000000000129,
      1623539.4170187458
    ],
    "numDrills": 3,
    "lastTime": 1607856593
  },
  "Haus-[de.noun.gender]-das": {
    "priorParams": [
      0.9079070388109558,
      1.0000000000000036,
      766072.9240637763
    ],
    "numDrills": 5,
    "lastTime": 1607668519
  },
  "the fall-[de.noun.en]-Fall": {
    "priorParams": [
      1.1687414935585088,
      1.0000000000000082,
      863843.7204158901
    ],
    "numDrills": 6,
    "lastTime": 1607895327
  },
  "Fall-[de.noun.gender]-der": {
    "priorParams": [
      1.1197116177346833,
      1.0000000000001388,
      786071.1508742713
    ],
    "numDrills": 11,
    "lastTime": 1607856701
  },
  "the people-[de.noun.en]-Leute": {
    "priorParams": [
      1.0227159522149862,
      0.9999999999999685,
      766072.9240637764
    ],
    "numDrills": 5,
    "lastTime": 1607668617
  },
  "Leute-[de.noun.gender]-pl.": {
    "priorParams": [
      0.9079762228250887,
      0.9999999999999822,
      766072.9240637763
    ],
    "numDrills": 5,
    "lastTime": 1607668559
  },
  "the work-[de.noun.en]-Arbeit": {
    "priorParams": [
      1.7977449695456182,
      1.0000000000000013,
      529667.4534656998
    ],
    "numDrills": 3,
    "lastTime": 1607668611
  },
  "Arbeit-[de.noun.gender]-die": {
    "priorParams": [
      0.9079879710539048,
      1.0000000000000067,
      766072.9240637763
    ],
    "numDrills": 5,
    "lastTime": 1607668563
  },
  "the percent-[de.noun.en]-Prozent": {
    "priorParams": [
      0.9072462778599296,
      0.9999999999999827,
      863843.7204158901
    ],
    "numDrills": 5,
    "lastTime": 1607668615
  },
  "Prozent-[de.noun.gender]-das": {
    "priorParams": [
      7.694429049905431,
      4.674950959091109,
      135270.47938265037
    ],
    "numDrills": 21,
    "lastTime": 1608151490
  },
  "the hand-[de.noun.en]-Hand": {
    "priorParams": [
      1.2803942733184333,
      0.9999999999982704,
      786071.1508742712
    ],
    "numDrills": 6,
    "lastTime": 1607895106
  },
  "Hand-[de.noun.gender]-die": {
    "priorParams": [
      1.2103593367055114,
      1.997239324260811,
      766072.9240637763
    ],
    "numDrills": 8,
    "lastTime": 1608237441,
    "lastResult": true
  },
  "the town-[de.noun.en]-Stadt": {
    "priorParams": [
      1.2315844423529008,
      1.0000000000049964,
      786071.1508742712
    ],
    "numDrills": 6,
    "lastTime": 1607856786
  },
  "Stadt-[de.noun.gender]-die": {
    "priorParams": [
      0.9079435888561674,
      1.000000000000035,
      766072.9240637763
    ],
    "numDrills": 5,
    "lastTime": 1607668524
  },
  "the gentleman-[de.noun.en]-Herr": {
    "priorParams": [
      1.7977562974079624,
      1.0000000000000044,
      529667.4534656998
    ],
    "numDrills": 3,
    "lastTime": 1607668633
  },
  "Herr-[de.noun.gender]-der": {
    "priorParams": [
      0.9079057334522114,
      1.0000000000000138,
      766072.9240637763
    ],
    "numDrills": 5,
    "lastTime": 1607668491
  },
  "the part/section-[de.noun.en]-Teil": {
    "priorParams": [
      1.0225097055313512,
      1.000000000000013,
      766072.9240637764
    ],
    "numDrills": 5,
    "lastTime": 1607668639
  },
  "Teil-[de.noun.gender]-der": {
    "priorParams": [
      2.8761855429300778,
      2.6156866277184654,
      289179.4157046195
    ],
    "numDrills": 17,
    "lastTime": 1608067067
  },
  "the problem-[de.noun.en]-Problem": {
    "priorParams": [
      0.9072856368310099,
      0.999999999999993,
      863843.7204158901
    ],
    "numDrills": 5,
    "lastTime": 1607668613
  },
  "Problem-[de.noun.gender]-das": {
    "priorParams": [
      0.9078913745058803,
      1.000000000000004,
      766072.9240637763
    ],
    "numDrills": 5,
    "lastTime": 1607668525
  },
  "the world-[de.noun.en]-Welt": {
    "priorParams": [
      0.9737435917203677,
      1.718086130941856,
      863843.7204158901
    ],
    "numDrills": 8,
    "lastTime": 1607895150
  },
  "Welt-[de.noun.gender]-die": {
    "priorParams": [
      3.5176861319270865,
      5.027357810113451,
      213143.23576551175
    ],
    "numDrills": 15,
    "lastTime": 1608151453
  },
  "the right/law-[de.noun.en]-Recht": {
    "priorParams": [
      1.318010294168727,
      0.9999999999999997,
      766072.9240637764
    ],
    "numDrills": 6,
    "lastTime": 1607895390
  },
  "Recht-[de.noun.gender]-das": {
    "priorParams": [
      0.9077960833165944,
      0.9999999999999656,
      766072.9240637763
    ],
    "numDrills": 5,
    "lastTime": 1607668497
  },
  "the end-[de.noun.en]-Ende": {
    "priorParams": [
      1.0227472808251563,
      1.0000000000000338,
      766072.9240637764
    ],
    "numDrills": 5,
    "lastTime": 1607668626
  },
  "Ende-[de.noun.gender]-das": {
    "priorParams": [
      3.2964278527241135,
      2.2797802035679084,
      281822.4792011548
    ],
    "numDrills": 10,
    "lastTime": 1608267803,
    "lastResult": true
  },
  "the million-[de.noun.en]-Million": {
    "priorParams": [
      1.1686025795429658,
      1.0000000000000229,
      863843.7204158901
    ],
    "numDrills": 6,
    "lastTime": 1607895332
  },
  "Million-[de.noun.gender]-die": {
    "priorParams": [
      0.9079305352685845,
      0.9999999999999902,
      766072.9240637763
    ],
    "numDrills": 5,
    "lastTime": 1607668552
  },
  "the school-[de.noun.en]-Schule": {
    "priorParams": [
      0.7027719734055645,
      0.9999999999999825,
      1623539.4170187458
    ],
    "numDrills": 3,
    "lastTime": 1607856657
  },
  "Schule-[de.noun.gender]-die": {
    "priorParams": [
      0.9078443815906355,
      1.0000000000000038,
      766072.9240637763
    ],
    "numDrills": 5,
    "lastTime": 1607668516
  },
  "the week-[de.noun.en]-Woche": {
    "priorParams": [
      0.7025699456650939,
      1.0,
      1623539.4170187458
    ],
    "numDrills": 3,
    "lastTime": 1607856597
  },
  "Woche-[de.noun.gender]-die": {
    "priorParams": [
      0.9077908618815793,
      0.9999999999999973,
      766072.9240637763
    ],
    "numDrills": 5,
    "lastTime": 1607668499
  },
  "the father-[de.noun.en]-Vater": {
    "priorParams": [
      1.3179554691009439,
      1.0000000000000075,
      766072.9240637764
    ],
    "numDrills": 6,
    "lastTime": 1607895381
  },
  "Vater-[de.noun.gender]-der": {
    "priorParams": [
      0.9078691834070014,
      0.9999999999999963,
      766072.9240637763
    ],
    "numDrills": 5,
    "lastTime": 1607668501
  },
  "the side-[de.noun.en]-Seite": {
    "priorParams": [
      1.02211026575167,
      0.9999999999999618,
      766072.9240637764
    ],
    "numDrills": 5,
    "lastTime": 1607668635
  },
  "Seite-[de.noun.gender]-die": {
    "priorParams": [
      0.9078809316358267,
      1.0000000000000107,
      766072.9240637763
    ],
    "numDrills": 5,
    "lastTime": 1607668541
  },
  "the page-[de.noun.en]-Seite": {
    "priorParams": [
      0.7026173729090507,
      1.0000000000000109,
      1623539.4170187458
    ],
    "numDrills": 3,
    "lastTime": 1607856590
  },
  "the life-[de.noun.en]-Leben": {
    "priorParams": [
      1.168310860110347,
      1.000000000000008,
      863843.7204158901
    ],
    "numDrills": 6,
    "lastTime": 1607895142
  },
  "Leben-[de.noun.gender]-das": {
    "priorParams": [
      16.627757061017082,
      8.45227391012853,
      48497.21532198135
    ],
    "numDrills": 22,
    "lastTime": 1608237396,
    "lastResult": true
  },
  "the mother-[de.noun.en]-Mutter": {
    "priorParams": [
      1.798396321630305,
      1.0000000000000067,
      529667.4534656998
    ],
    "numDrills": 3,
    "lastTime": 1607668677
  },
  "Mutter-[de.noun.gender]-die": {
    "priorParams": [
      0.9078757102008032,
      0.9999999999999953,
      766072.9240637763
    ],
    "numDrills": 5,
    "lastTime": 1607668520
  },
  "the grounding/basis/reason-[de.noun.en]-Grund": {
    "priorParams": [
      0.9770583954798935,
      1.7014647058748518,
      863843.7204158901
    ],
    "numDrills": 8,
    "lastTime": 1607895184
  },
  "Grund-[de.noun.gender]-der": {
    "priorParams": [
      3.5285977643788775,
      2.2651618862906635,
      326086.21775173873
    ],
    "numDrills": 15,
    "lastTime": 1608237426,
    "lastResult": true
  },
  "the eye-[de.noun.en]-Auge": {
    "priorParams": [
      0.7028009225025348,
      0.9999999999999866,
      1623539.4170187458
    ],
    "numDrills": 4,
    "lastTime": 1607856639
  },
  "Auge-[de.noun.gender]-das": {
    "priorParams": [
      0.9078639619719883,
      1.0000000000000153,
      766072.9240637763
    ],
    "numDrills": 5,
    "lastTime": 1607668542
  },
  "the word-[de.noun.en]-Wort": {
    "priorParams": [
      1.1688109505662596,
      0.9999999999999885,
      863843.7204158901
    ],
    "numDrills": 6,
    "lastTime": 1607895365
  },
  "Wort-[de.noun.gender]-das": {
    "priorParams": [
      3.6357855518008697,
      2.2578575774140153,
      317790.34512605733
    ],
    "numDrills": 10,
    "lastTime": 1608237443,
    "lastResult": true
  },
  "the money-[de.noun.en]-Geld": {
    "priorParams": [
      1.0227107307799521,
      1.0000000000000222,
      766072.9240637764
    ],
    "numDrills": 5,
    "lastTime": 1607668628
  },
  "Geld-[de.noun.gender]-das": {
    "priorParams": [
      0.9078652673307486,
      0.9999999999999851,
      766072.9240637763
    ],
    "numDrills": 5,
    "lastTime": 1607668510
  },
  "the thing-[de.noun.en]-Sache": {
    "priorParams": [
      1.1114561872363806,
      1.017734109722689,
      886394.2402254906
    ],
    "numDrills": 8,
    "lastTime": 1607895161
  },
  "Sache-[de.noun.gender]-die": {
    "priorParams": [
      1.210209643311706,
      1.9970150511792915,
      766072.9240637763
    ],
    "numDrills": 8,
    "lastTime": 1608237445,
    "lastResult": true
  },
  "the type/kind-[de.noun.en]-Art": {
    "priorParams": [
      1.2305896214662726,
      1.0000000000003932,
      786071.1508742712
    ],
    "numDrills": 6,
    "lastTime": 1607856720
  },
  "Art-[de.noun.gender]-die": {
    "priorParams": [
      2.9773383569541676,
      1.739044450925174,
      289179.4157046195
    ],
    "numDrills": 15,
    "lastTime": 1607895410
  },
  "the area/region-[de.noun.en]-Bereich": {
    "priorParams": [
      1.1117481826227986,
      1.0173266849855764,
      886394.2402254906
    ],
    "numDrills": 9,
    "lastTime": 1607895164
  },
  "Bereich-[de.noun.gender]-der": {
    "priorParams": [
      6.136606767929498,
      3.858772150327594,
      131829.09914060746
    ],
    "numDrills": 18,
    "lastTime": 1608151396
  },
  "the way/path-[de.noun.en]-Weg": {
    "priorParams": [
      0.7026352351178135,
      1.0000000000000007,
      1623539.4170187458
    ],
    "numDrills": 3,
    "lastTime": 1607856595
  },
  "Weg-[de.noun.gender]-der": {
    "priorParams": [
      0.9078704887657445,
      0.9999999999999687,
      766072.9240637763
    ],
    "numDrills": 5,
    "lastTime": 1607668545
  },
  "the hour-[de.noun.en]-Stunde": {
    "priorParams": [
      1.0221272354155186,
      1.0000000000000207,
      766072.9240637764
    ],
    "numDrills": 5,
    "lastTime": 1607668651
  },
  "Stunde-[de.noun.gender]-die": {
    "priorParams": [
      0.9078326333618195,
      1.000000000000004,
      766072.9240637763
    ],
    "numDrills": 5,
    "lastTime": 1607668522
  },
  "the name-[de.noun.en]-Name": {
    "priorParams": [
      1.1688503095373362,
      1.0000000000000036,
      863843.7204158901
    ],
    "numDrills": 6,
    "lastTime": 1607895358
  },
  "Name-[de.noun.gender]-der": {
    "priorParams": [
      0.9074253614295922,
      1.0000000000000044,
      766072.9240637763
    ],
    "numDrills": 5,
    "lastTime": 1607668514
  },
  "the history-[de.noun.en]-Geschichte": {
    "priorParams": [
      0.9727225012673283,
      1.7228405998566194,
      863843.7204158901
    ],
    "numDrills": 8,
    "lastTime": 1607895137
  },
  "Geschichte-[de.noun.gender]-die": {
    "priorParams": [
      1.2099424388401279,
      1.9971381973044744,
      766072.9240637763
    ],
    "numDrills": 8,
    "lastTime": 1608237429,
    "lastResult": true
  },
  "the society/company-[de.noun.en]-Gesellschaft": {
    "priorParams": [
      1.797856360191997,
      1.000000000000011,
      529667.4534656998
    ],
    "numDrills": 3,
    "lastTime": 1607668675
  },
  "Gesellschaft-[de.noun.gender]-die": {
    "priorParams": [
      2.032448347649431,
      2.9779071834430084,
      404083.2363106646
    ],
    "numDrills": 11,
    "lastTime": 1608151442
  },
  "the head-[de.noun.en]-Kopf": {
    "priorParams": [
      1.7983491222038692,
      1.0000000000000053,
      529667.4534656998
    ],
    "numDrills": 3,
    "lastTime": 1607668669
  },
  "Kopf-[de.noun.gender]-der": {
    "priorParams": [
      0.9074096971245162,
      1.000000000000027,
      766072.9240637763
    ],
    "numDrills": 5,
    "lastTime": 1607668518
  },
  "the pair/couple-[de.noun.en]-Paar": {
    "priorParams": [
      1.1687959015479203,
      1.0000000000000047,
      863843.7204158901
    ],
    "numDrills": 6,
    "lastTime": 1607895368
  },
  "Paar-[de.noun.gender]-das": {
    "priorParams": [
      1.2674720245290412,
      0.9999999999999893,
      766072.9240637763
    ],
    "numDrills": 6,
    "lastTime": 1607944333
  },
  "the likelihood/possibility-[de.noun.en]-M\u00f6glichkeit": {
    "priorParams": [
      1.1112282122144652,
      1.0181314078238195,
      886394.2402254906
    ],
    "numDrills": 8,
    "lastTime": 1607895157
  },
  "M\u00f6glichkeit-[de.noun.gender]-die": {
    "priorParams": [
      0.9074344989408919,
      0.9999999999999952,
      766072.9240637763
    ],
    "numDrills": 5,
    "lastTime": 1607668513
  },
  "the enterprise/company-[de.noun.en]-Unternehmen": {
    "priorParams": [
      1.2316531384224887,
      1.0000000000145404,
      786071.1508742712
    ],
    "numDrills": 6,
    "lastTime": 1607856781
  },
  "Unternehmen-[de.noun.gender]-das": {
    "priorParams": [
      1.983478091558757,
      3.0821892590343056,
      414631.77282229665
    ],
    "numDrills": 17,
    "lastTime": 1608151444
  },
  "the picture-[de.noun.en]-Bild": {
    "priorParams": [
      1.0227707772827865,
      1.0000000000000355,
      766072.9240637764
    ],
    "numDrills": 5,
    "lastTime": 1607668631
  },
  "Bild-[de.noun.gender]-das": {
    "priorParams": [
      0.9074031703307354,
      1.0000000000000109,
      766072.9240637763
    ],
    "numDrills": 5,
    "lastTime": 1607668509
  },
  "the book-[de.noun.en]-Buch": {
    "priorParams": [
      0.7027399446174506,
      1.000000000000003,
      1623539.4170187458
    ],
    "numDrills": 3,
    "lastTime": 1607856646
  },
  "Buch-[de.noun.gender]-das": {
    "priorParams": [
      1.2036948063749078,
      1.0000000000000093,
      766072.9240637763
    ],
    "numDrills": 6,
    "lastTime": 1607895486
  },
  "the water-[de.noun.en]-Wasser": {
    "priorParams": [
      0.7027805965408401,
      1.000000000000003,
      1623539.4170187458
    ],
    "numDrills": 3,
    "lastTime": 1607856644
  },
  "Wasser-[de.noun.gender]-das": {
    "priorParams": [
      1.2036895849398639,
      0.9999999999999741,
      766072.9240637763
    ],
    "numDrills": 6,
    "lastTime": 1607895488
  },
  "the place-[de.noun.en]-Stelle": {
    "priorParams": [
      0.907233544075193,
      0.9999999999999992,
      863843.7204158901
    ],
    "numDrills": 5,
    "lastTime": 1607668624
  },
  "Stelle-[de.noun.gender]-die": {
    "priorParams": [
      0.9346227574720386,
      0.9999999999999714,
      863843.7204158901
    ],
    "numDrills": 6,
    "lastTime": 1607856485
  },
  "the form/shape-[de.noun.en]-Form": {
    "priorParams": [
      0.9073273110356744,
      1.0000000000000107,
      863843.7204158901
    ],
    "numDrills": 5,
    "lastTime": 1607668637
  },
  "Form-[de.noun.gender]-die": {
    "priorParams": [
      1.107757199370317,
      2.0329796740553148,
      863843.7204158901
    ],
    "numDrills": 9,
    "lastTime": 1608237474,
    "lastResult": true
  },
  "the mark (currency)-[de.noun.en]-Mark": {
    "priorParams": [
      1.168806320099095,
      1.0000000000000278,
      863843.7204158901
    ],
    "numDrills": 6,
    "lastTime": 1607895337
  },
  "Mark-[de.noun.gender]-die": {
    "priorParams": [
      0.7575317359755509,
      0.9999999999999796,
      999521.1606876455
    ],
    "numDrills": 9,
    "lastTime": 1607809824
  },
  "the development-[de.noun.en]-Entwicklung": {
    "priorParams": [
      3.346134643166097,
      1.6742909604801954,
      281822.4792011548
    ],
    "numDrills": 8,
    "lastTime": 1607895146
  },
  "Entwicklung-[de.noun.gender]-die": {
    "priorParams": [
      0.9345972899025161,
      0.9999999999999923,
      863843.7204158901
    ],
    "numDrills": 5,
    "lastTime": 1607856465
  },
  "the month-[de.noun.en]-Monat": {
    "priorParams": [
      1.168460192677051,
      1.0000000000000158,
      863843.7204158901
    ],
    "numDrills": 6,
    "lastTime": 1607895133
  },
  "Monat-[de.noun.gender]-der": {
    "priorParams": [
      0.7575177292685701,
      1.0000000000000588,
      999521.1606876455
    ],
    "numDrills": 9,
    "lastTime": 1607809818
  },
  "the family-[de.noun.en]-Familie": {
    "priorParams": [
      0.7027725893438073,
      1.0000000000000016,
      1623539.4170187458
    ],
    "numDrills": 3,
    "lastTime": 1607856610
  },
  "Familie-[de.noun.gender]-die": {
    "priorParams": [
      0.9347199972829142,
      1.0000000000000362,
      863843.7204158901
    ],
    "numDrills": 5,
    "lastTime": 1607856559
  },
  "the morning-[de.noun.en]-Morgen": {
    "priorParams": [
      0.7025379168769659,
      1.000000000000004,
      1623539.4170187458
    ],
    "numDrills": 3,
    "lastTime": 1607856572
  },
  "Morgen-[de.noun.gender]-der": {
    "priorParams": [
      0.891286215091448,
      1.0000000000000042,
      863843.7204158901
    ],
    "numDrills": 5,
    "lastTime": 1607819077
  },
  "the evening-[de.noun.en]-Abend": {
    "priorParams": [
      1.1685759543566463,
      1.0000000000000147,
      863843.7204158901
    ],
    "numDrills": 6,
    "lastTime": 1607895319
  },
  "Abend-[de.noun.gender]-der": {
    "priorParams": [
      0.9345903442017355,
      0.9999999999999597,
      863843.7204158901
    ],
    "numDrills": 5,
    "lastTime": 1607856467
  },
  "the task/asg./job-[de.noun.en]-Aufgabe": {
    "priorParams": [
      1.899793905432295,
      0.9999999999999737,
      529667.4534656998
    ],
    "numDrills": 3,
    "lastTime": 1607722270
  },
  "Aufgabe-[de.noun.gender]-die": {
    "priorParams": [
      0.9345671918658168,
      0.9999999999999887,
      863843.7204158901
    ],
    "numDrills": 5,
    "lastTime": 1607856463
  },
  "the university-[de.noun.en]-Universit\u00e4t": {
    "priorParams": [
      0.7026450901295415,
      1.000000000000003,
      1623539.4170187458
    ],
    "numDrills": 3,
    "lastTime": 1607856607
  },
  "Universit\u00e4t-[de.noun.gender]-die": {
    "priorParams": [
      0.9345579309314515,
      1.0,
      863843.7204158901
    ],
    "numDrills": 5,
    "lastTime": 1607856441
  },
  "the sense/meaning-[de.noun.en]-Sinn": {
    "priorParams": [
      2.6011946030543793,
      1.976568222999908,
      358348.64465603925
    ],
    "numDrills": 7,
    "lastTime": 1608237439,
    "lastResult": true
  },
  "Sinn-[de.noun.gender]-der": {
    "priorParams": [
      0.757498720166271,
      0.9999999999999598,
      999521.1606876455
    ],
    "numDrills": 9,
    "lastTime": 1607809809
  },
  "the state-[de.noun.en]-Staat": {
    "priorParams": [
      0.7025964310091267,
      1.0000000000000047,
      1623539.4170187458
    ],
    "numDrills": 3,
    "lastTime": 1607856585
  },
  "Staat-[de.noun.gender]-der": {
    "priorParams": [
      1.8751034247712903,
      2.962631566399688,
      367703.2860328024
    ],
    "numDrills": 14,
    "lastTime": 1608236675
  },
  "the goal-[de.noun.en]-Ziel": {
    "priorParams": [
      1.230866950052081,
      0.9999999999965955,
      786071.1508742712
    ],
    "numDrills": 6,
    "lastTime": 1607856754
  },
  "Ziel-[de.noun.gender]-das": {
    "priorParams": [
      8.21181066534051,
      4.390873693000478,
      119960.41556021891
    ],
    "numDrills": 24,
    "lastTime": 1608151447
  },
  "the destination-[de.noun.en]-Ziel": {
    "priorParams": [
      1.2313287403099953,
      0.999999999999645,
      786071.1508742712
    ],
    "numDrills": 6,
    "lastTime": 1607856784
  },
  "the friend (m)-[de.noun.en]-Freund": {
    "priorParams": [
      0.7027436402468457,
      0.9999999999999817,
      1623539.4170187458
    ],
    "numDrills": 3,
    "lastTime": 1607856622
  },
  "Freund-[de.noun.gender]-der": {
    "priorParams": [
      0.9345579309314407,
      0.9999999999999977,
      863843.7204158901
    ],
    "numDrills": 5,
    "lastTime": 1607856487
  },
  "the friend (f)-[de.noun.en]-Freundin": {
    "priorParams": [
      1.3179854923523642,
      0.9999999999999873,
      766072.9240637764
    ],
    "numDrills": 6,
    "lastTime": 1607895401
  },
  "Freundin-[de.noun.gender]-die": {
    "priorParams": [
      0.9345336209787374,
      1.0000000000000155,
      863843.7204158901
    ],
    "numDrills": 5,
    "lastTime": 1607856446
  },
  "the topic/theme-[de.noun.en]-Thema": {
    "priorParams": [
      1.1685516444039394,
      1.0000000000000089,
      863843.7204158901
    ],
    "numDrills": 6,
    "lastTime": 1607895304
  },
  "Thema-[de.noun.gender]-das": {
    "priorParams": [
      0.9345185719603676,
      0.9999999999999869,
      863843.7204158901
    ],
    "numDrills": 5,
    "lastTime": 1607856451
  },
  "the person-[de.noun.en]-Person": {
    "priorParams": [
      0.7028083137613235,
      0.999999999999979,
      1623539.4170187458
    ],
    "numDrills": 3,
    "lastTime": 1607856675
  },
  "Person-[de.noun.gender]-die": {
    "priorParams": [
      0.6717552971893012,
      1.0000000000000262,
      1127086.0135646083
    ],
    "numDrills": 10,
    "lastTime": 1607809829
  },
  "the euro (currency)-[de.noun.en]-Euro": {
    "priorParams": [
      1.3181369139681736,
      1.000000000000035,
      766072.9240637764
    ],
    "numDrills": 6,
    "lastTime": 1607895445
  },
  "Euro-[de.noun.gender]-der": {
    "priorParams": [
      2.3901283833425544,
      3.2971225765203216,
      367703.2860328025
    ],
    "numDrills": 20,
    "lastTime": 1608151450
  },
  "the night-[de.noun.en]-Nacht": {
    "priorParams": [
      0.7027251620998579,
      1.0000000000000178,
      1623539.4170187458
    ],
    "numDrills": 3,
    "lastTime": 1607856625
  },
  "Nacht-[de.noun.gender]-die": {
    "priorParams": [
      0.8805632107087366,
      1.0000000000000044,
      863843.7204158901
    ],
    "numDrills": 5,
    "lastTime": 1607809866
  },
  "the thing-[de.noun.en]-Ding": {
    "priorParams": [
      0.70275287932035,
      1.000000000000009,
      1623539.4170187458
    ],
    "numDrills": 3,
    "lastTime": 1607856650
  },
  "Ding-[de.noun.gender]-das": {
    "priorParams": [
      0.9344942620076592,
      1.0000000000000344,
      863843.7204158901
    ],
    "numDrills": 5,
    "lastTime": 1607856443
  },
  "the room/space-[de.noun.en]-Raum": {
    "priorParams": [
      1.3179646066122335,
      0.999999999999986,
      766072.9240637764
    ],
    "numDrills": 6,
    "lastTime": 1607895383
  },
  "Raum-[de.noun.gender]-der": {
    "priorParams": [
      2.976793115675421,
      1.9325790331224635,
      367703.2860328025
    ],
    "numDrills": 16,
    "lastTime": 1608237457,
    "lastResult": true
  },
  "the look/glance/view-[de.noun.en]-Blick": {
    "priorParams": [
      1.2307473679997136,
      1.0000000000062348,
      786071.1508742712
    ],
    "numDrills": 6,
    "lastTime": 1607856749
  },
  "Blick-[de.noun.gender]-der": {
    "priorParams": [
      0.6716985135905094,
      0.9999999999999982,
      1127086.0135646083
    ],
    "numDrills": 9,
    "lastTime": 1607809794
  },
  "the place-[de.noun.en]-Platz": {
    "priorParams": [
      1.23129948087081,
      1.0000000000063072,
      786071.1508742712
    ],
    "numDrills": 6,
    "lastTime": 1607856768
  },
  "Platz-[de.noun.gender]-der": {
    "priorParams": [
      0.6717242436587247,
      0.9999999999999443,
      1127086.0135646083
    ],
    "numDrills": 9,
    "lastTime": 1607809811
  },
  "the public square-[de.noun.en]-Platz": {
    "priorParams": [
      1.0229130613872968,
      1.0000000000000269,
      766072.9240637764
    ],
    "numDrills": 5,
    "lastTime": 1607668641
  },
  "the number-[de.noun.en]-Zahl": {
    "priorParams": [
      0.9733014771062599,
      1.72010010254058,
      863843.7204158901
    ],
    "numDrills": 8,
    "lastTime": 1607895140
  },
  "Zahl-[de.noun.gender]-die": {
    "priorParams": [
      0.8912364375692293,
      0.9999999999999739,
      863843.7204158901
    ],
    "numDrills": 5,
    "lastTime": 1607819084
  },
  "the system-[de.noun.en]-System": {
    "priorParams": [
      1.1683374852966695,
      1.0000000000000269,
      863843.7204158901
    ],
    "numDrills": 6,
    "lastTime": 1607895128
  },
  "System-[de.noun.gender]-das": {
    "priorParams": [
      0.6717091605152731,
      0.9999999999999715,
      1127086.0135646083
    ],
    "numDrills": 10,
    "lastTime": 1607809819
  },
  "the clock/watch-[de.noun.en]-Uhr": {
    "priorParams": [
      1.0221546479494346,
      1.000000000000003,
      766072.9240637764
    ],
    "numDrills": 5,
    "lastTime": 1607668643
  },
  "Uhr-[de.noun.gender]-die": {
    "priorParams": [
      0.8805446888399905,
      0.9999999999999929,
      863843.7204158901
    ],
    "numDrills": 5,
    "lastTime": 1607809868
  },
  "the parents-[de.noun.en]-Eltern": {
    "priorParams": [
      1.168770433978404,
      1.0000000000000029,
      863843.7204158901
    ],
    "numDrills": 6,
    "lastTime": 1607895356
  },
  "Eltern-[de.noun.gender]-pl.": {
    "priorParams": [
      0.8911901328973776,
      0.9999999999999959,
      863843.7204158901
    ],
    "numDrills": 5,
    "lastTime": 1607819060
  },
  "the street-[de.noun.en]-Stra\u00dfe": {
    "priorParams": [
      0.7025699456651044,
      1.0000000000000062,
      1623539.4170187458
    ],
    "numDrills": 3,
    "lastTime": 1607856567
  },
  "Stra\u00dfe-[de.noun.gender]-die": {
    "priorParams": [
      0.9344699520549453,
      1.0000000000000082,
      863843.7204158901
    ],
    "numDrills": 5,
    "lastTime": 1607856449
  },
  "the minute-[de.noun.en]-Minute": {
    "priorParams": [
      1.1687009769706354,
      1.000000000000008,
      863843.7204158901
    ],
    "numDrills": 6,
    "lastTime": 1607895299
  },
  "Minute-[de.noun.gender]-die": {
    "priorParams": [
      0.8912179157004824,
      0.9999999999999839,
      863843.7204158901
    ],
    "numDrills": 5,
    "lastTime": 1607819074
  },
  "the group-[de.noun.en]-Gruppe": {
    "priorParams": [
      0.7026469379442429,
      0.9999999999999999,
      1623539.4170187458
    ],
    "numDrills": 3,
    "lastTime": 1607856618
  },
  "Gruppe-[de.noun.gender]-die": {
    "priorParams": [
      0.8805481616903982,
      0.9999999999999777,
      863843.7204158901
    ],
    "numDrills": 5,
    "lastTime": 1607809863
  },
  "the value/worth-[de.noun.en]-Wert": {
    "priorParams": [
      1.1686975041202472,
      0.9999999999999982,
      863843.7204158901
    ],
    "numDrills": 6,
    "lastTime": 1607895341
  },
  "Wert-[de.noun.gender]-der": {
    "priorParams": [
      4.958240148498329,
      3.6913715175592996,
      116908.53457465375
    ],
    "numDrills": 9,
    "lastTime": 1608236653
  },
  "the face-[de.noun.en]-Gesicht": {
    "priorParams": [
      1.1209775259108947,
      1.9982447009489823,
      766072.9240637764
    ],
    "numDrills": 7,
    "lastTime": 1608236743
  },
  "Gesicht-[de.noun.gender]-das": {
    "priorParams": [
      0.8804520794963062,
      1.0000000000000269,
      863843.7204158901
    ],
    "numDrills": 5,
    "lastTime": 1607809839
  },
  "the language-[de.noun.en]-Sprache": {
    "priorParams": [
      2.9262564636074835,
      1.9673618181556431,
      281822.4792011548
    ],
    "numDrills": 9,
    "lastTime": 1607895452
  },
  "Sprache-[de.noun.gender]-die": {
    "priorParams": [
      0.8804393457115499,
      1.0000000000000462,
      863843.7204158901
    ],
    "numDrills": 5,
    "lastTime": 1607809841
  },
  "the beginning-[de.noun.en]-Anfang": {
    "priorParams": [
      1.2308580450033477,
      1.000000000008482,
      786071.1508742712
    ],
    "numDrills": 6,
    "lastTime": 1607856770
  },
  "Anfang-[de.noun.gender]-der": {
    "priorParams": [
      1.848714115627867,
      3.1758680830206862,
      367703.2860328025
    ],
    "numDrills": 16,
    "lastTime": 1608236754
  },
  "the place/location-[de.noun.en]-Ort": {
    "priorParams": [
      1.1166521115344028,
      1.0000000000012252,
      886394.2402254906
    ],
    "numDrills": 7,
    "lastTime": 1607895309
  },
  "Ort-[de.noun.gender]-der": {
    "priorParams": [
      1.1069811916179702,
      2.03650688701755,
      863843.7204158901
    ],
    "numDrills": 9,
    "lastTime": 1608237458,
    "lastResult": true
  },
  "the town-[de.noun.en]-Ort": {
    "priorParams": [
      0.9851800852039684,
      1.7074562073117803,
      886394.2402254909
    ],
    "numDrills": 10,
    "lastTime": 1608267778,
    "lastResult": true
  },
  "the moment-[de.noun.en]-Moment": {
    "priorParams": [
      1.0229091453110393,
      1.0000000000000189,
      766072.9240637764
    ],
    "numDrills": 5,
    "lastTime": 1607668645
  },
  "Moment-[de.noun.gender]-der": {
    "priorParams": [
      4.190155373302643,
      6.442358080487738,
      193953.7727479207
    ],
    "numDrills": 25,
    "lastTime": 1608151399
  },
  "the result/consequence-[de.noun.en]-Folge": {
    "priorParams": [
      0.7027812124790704,
      0.9999999999999842,
      1623539.4170187458
    ],
    "numDrills": 3,
    "lastTime": 1607856615
  },
  "Folge-[de.noun.gender]-die": {
    "priorParams": [
      0.8805331126720335,
      0.9999999999999535,
      863843.7204158901
    ],
    "numDrills": 5,
    "lastTime": 1607809876
  },
  "the interest-[de.noun.en]-Interesse": {
    "priorParams": [
      1.168722971689763,
      1.0000000000000033,
      863843.7204158901
    ],
    "numDrills": 6,
    "lastTime": 1607895351
  },
  "Interesse-[de.noun.gender]-das": {
    "priorParams": [
      1.6443000554121887,
      3.2367657818912408,
      367703.2860328025
    ],
    "numDrills": 18,
    "lastTime": 1608067106
  },
  "the billion-[de.noun.en]-Milliarde": {
    "priorParams": [
      1.230751184449169,
      1.0000000000010978,
      786071.1508742712
    ],
    "numDrills": 6,
    "lastTime": 1607856744
  },
  "Milliarde-[de.noun.gender]-die": {
    "priorParams": [
      0.8804405033283398,
      0.9999999999999682,
      863843.7204158901
    ],
    "numDrills": 5,
    "lastTime": 1607809837
  },
  "the role-[de.noun.en]-Rolle": {
    "priorParams": [
      1.2307244693100534,
      1.000000000001985,
      786071.1508742712
    ],
    "numDrills": 6,
    "lastTime": 1607856717
  },
  "Rolle-[de.noun.gender]-die": {
    "priorParams": [
      0.8804752318322268,
      0.9999999999999736,
      863843.7204158901
    ],
    "numDrills": 5,
    "lastTime": 1607809851
  },
  "the roll-[de.noun.en]-Rolle": {
    "priorParams": [
      1.230816064072694,
      0.9999999999990854,
      786071.1508742712
    ],
    "numDrills": 6,
    "lastTime": 1607856751
  },
  "the door-[de.noun.en]-T\u00fcr": {
    "priorParams": [
      1.1688572552381105,
      1.0000000000000069,
      863843.7204158901
    ],
    "numDrills": 6,
    "lastTime": 1607895353
  },
  "T\u00fcr-[de.noun.gender]-die": {
    "priorParams": [
      0.9344271202334802,
      1.0000000000000275,
      863843.7204158901
    ],
    "numDrills": 5,
    "lastTime": 1607856448
  },
  "the pupil/student (m)-[de.noun.en]-Sch\u00fcler": {
    "priorParams": [
      1.1682934958583933,
      1.000000000000012,
      863843.7204158901
    ],
    "numDrills": 6,
    "lastTime": 1607895112
  },
  "Sch\u00fcler-[de.noun.gender]-der": {
    "priorParams": [
      0.8911623500942831,
      1.0000000000000406,
      863843.7204158901
    ],
    "numDrills": 5,
    "lastTime": 1607819081
  },
  "the meaning-[de.noun.en]-Bedeutung": {
    "priorParams": [
      0.9073585666891767,
      1.0000000000000113,
      863843.7204158901
    ],
    "numDrills": 5,
    "lastTime": 1607668621
  },
  "Bedeutung-[de.noun.gender]-die": {
    "priorParams": [
      0.8805111179529118,
      0.9999999999999812,
      863843.7204158901
    ],
    "numDrills": 5,
    "lastTime": 1607809869
  },
  "the significance-[de.noun.en]-Bedeutung": {
    "priorParams": [
      1.318019431680039,
      1.0000000000000242,
      766072.9240637764
    ],
    "numDrills": 6,
    "lastTime": 1607895378
  },
  "the text-[de.noun.en]-Text": {
    "priorParams": [
      1.8996372033365885,
      0.9999999999999909,
      529667.4534656998
    ],
    "numDrills": 3,
    "lastTime": 1607722232
  },
  "Text-[de.noun.gender]-der": {
    "priorParams": [
      1.8256319211803833,
      1.0000000000000575,
      414631.77282229677
    ],
    "numDrills": 10,
    "lastTime": 1607809805
  },
  "the result-[de.noun.en]-Ergebnis": {
    "priorParams": [
      1.2307855324852506,
      0.9999999999993952,
      786071.1508742712
    ],
    "numDrills": 6,
    "lastTime": 1607856733
  },
  "Ergebnis-[de.noun.gender]-das": {
    "priorParams": [
      1.564253032528786,
      2.5618730684706246,
      527221.0160217481
    ],
    "numDrills": 17,
    "lastTime": 1608151477
  },
  "the war-[de.noun.en]-Krieg": {
    "priorParams": [
      5.347939381452401,
      3.0506221738385895,
      219722.16684803704
    ],
    "numDrills": 8,
    "lastTime": 1608237467,
    "lastResult": true
  },
  "Krieg-[de.noun.gender]-der": {
    "priorParams": [
      0.8804891232337823,
      1.000000000000029,
      863843.7204158901
    ],
    "numDrills": 5,
    "lastTime": 1607809843
  },
  "the way/manner-[de.noun.en]-Weise": {
    "priorParams": [
      1.2308873044417152,
      1.000000000005991,
      786071.1508742712
    ],
    "numDrills": 6,
    "lastTime": 1607856757
  },
  "Weise-[de.noun.gender]-die": {
    "priorParams": [
      0.8804532371130991,
      1.0000000000000142,
      863843.7204158901
    ],
    "numDrills": 5,
    "lastTime": 1607809850
  },
  "the rule/government-[de.noun.en]-Regierung": {
    "priorParams": [
      1.230573083525452,
      0.9999999999911774,
      786071.1508742712
    ],
    "numDrills": 6,
    "lastTime": 1607856713
  },
  "Regierung-[de.noun.gender]-die": {
    "priorParams": [
      0.8804590251970885,
      0.9999999999999648,
      863843.7204158901
    ],
    "numDrills": 5,
    "lastTime": 1607809865
  },
  "the piece/bit/part-[de.noun.en]-St\u00fcck": {
    "priorParams": [
      2.5545379562004147,
      1.9560791108254427,
      326086.2177517387
    ],
    "numDrills": 7,
    "lastTime": 1608151474
  },
  "St\u00fcck-[de.noun.gender]-das": {
    "priorParams": [
      3.0156102503336015,
      6.453123294961902,
      218707.3102002931
    ],
    "numDrills": 22,
    "lastTime": 1608236649
  },
  "the apartment-[de.noun.en]-Wohnung": {
    "priorParams": [
      1.168540068235965,
      0.9999999999999751,
      863843.7204158901
    ],
    "numDrills": 6,
    "lastTime": 1607895317
  },
  "Wohnung-[de.noun.gender]-die": {
    "priorParams": [
      0.8911033116376699,
      0.9999999999999793,
      863843.7204158901
    ],
    "numDrills": 5,
    "lastTime": 1607819082
  },
  "the conversation-[de.noun.en]-Gespr\u00e4ch": {
    "priorParams": [
      1.279398180282768,
      0.9999999999923481,
      786071.1508742712
    ],
    "numDrills": 7,
    "lastTime": 1607895436
  },
  "Gespr\u00e4ch-[de.noun.gender]-das": {
    "priorParams": [
      2.31616366997876,
      4.016256219696174,
      281822.4792011548
    ],
    "numDrills": 13,
    "lastTime": 1608151488
  },
  "the o'clock-[de.noun.en]-Uhr": {
    "priorParams": [
      1.167951998903543,
      0.999999999999996,
      863843.7204158901
    ],
    "numDrills": 6,
    "lastTime": 1607895117
  },
  "the pupil/student (f)-[de.noun.en]-Sch\u00fclerin": {
    "priorParams": [
      1.1679357922683828,
      0.9999999999999921,
      863843.7204158901
    ],
    "numDrills": 6,
    "lastTime": 1607895115
  },
  "Sch\u00fclerin-[de.noun.gender]-die": {
    "priorParams": [
      0.9343379837401744,
      1.000000000000028,
      863843.7204158901
    ],
    "numDrills": 5,
    "lastTime": 1607856406
  },
  "the position/role-[de.noun.en]-Stelle": {
    "priorParams": [
      1.3732226084199868,
      0.9999999999999761,
      281822.4792011548
    ],
    "numDrills": 4,
    "lastTime": 1607944331
  }
}